{
  "15367410": {
    "home": {
      "fractionalValue": "11/10",
      "expected": 48,
      "actual": 52,
      "id": 21183246
    },
    "away": {
      "fractionalValue": "13/5",
      "expected": 28,
      "actual": 30,
      "id": 21183248
    }
  },
  "15367411": {
    "home": {
      "fractionalValue": "1/2",
      "expected": 67,
      "actual": 44,
      "id": 21183202
    },
    "away": null
  },
  "15275500": {
    "home": {
      "fractionalValue": "21/20",
      "expected": 49,
      "actual": 28,
      "id": 21202764
    },
    "away": {
      "fractionalValue": "16/5",
      "expected": 24,
      "actual": 11,
      "id": 21202765
    }
  },
  "14303587": {
    "home": {
      "fractionalValue": "7/10",
      "expected": 59,
      "actual": 63,
      "id": 21262724
    },
    "away": {
      "fractionalValue": "10/3",
      "expected": 23,
      "actual": 20,
      "id": 21262725
    }
  },
  "14303200": {
    "home": {
      "fractionalValue": "23/20",
      "expected": 47,
      "actual": 60,
      "id": 21262644
    },
    "away": {
      "fractionalValue": "9/4",
      "expected": 31,
      "actual": 14,
      "id": 21262645
    }
  },
  "15713283": {
    "home": {
      "fractionalValue": "9/5",
      "expected": 36,
      "actual": 45,
      "id": 21202841
    },
    "away": {
      "fractionalValue": "27/20",
      "expected": 43,
      "actual": 45,
      "id": 21202842
    }
  },
  "15713275": {
    "home": {
      "fractionalValue": "2/1",
      "expected": 33,
      "actual": 39,
      "id": 21202754
    },
    "away": {
      "fractionalValue": "5/4",
      "expected": 44,
      "actual": 48,
      "id": 21202755
    }
  },
  "15400143": {
    "home": {
      "fractionalValue": "19/20",
      "expected": 51,
      "actual": 42,
      "id": 21273136
    },
    "away": {
      "fractionalValue": "15/4",
      "expected": 21,
      "actual": 40,
      "id": 21273137
    }
  },
  "15329651": {
    "home": {
      "fractionalValue": "4/6",
      "expected": 60,
      "actual": 56,
      "id": 21274764
    },
    "away": null
  },
  "15416171": {
    "home": {
      "fractionalValue": "23/20",
      "expected": 47,
      "actual": 35,
      "id": 21274484
    },
    "away": {
      "fractionalValue": "9/5",
      "expected": 36,
      "actual": 45,
      "id": 21274485
    }
  },
  "15683243": {
    "home": {
      "fractionalValue": "13/5",
      "expected": 28,
      "actual": 30,
      "id": 21274773
    },
    "away": {
      "fractionalValue": "19/20",
      "expected": 51,
      "actual": 69,
      "id": 21274774
    }
  },
  "15683247": {
    "home": {
      "fractionalValue": "7/4",
      "expected": 36,
      "actual": 53,
      "id": 21274700
    },
    "away": {
      "fractionalValue": "7/5",
      "expected": 42,
      "actual": 48,
      "id": 21274701
    }
  },
  "15683251": {
    "home": {
      "fractionalValue": "1/1",
      "expected": 50,
      "actual": 52,
      "id": 21274775
    },
    "away": {
      "fractionalValue": "5/2",
      "expected": 29,
      "actual": 28,
      "id": 21274776
    }
  },
  "15362813": {
    "home": {
      "fractionalValue": "9/50",
      "expected": 85,
      "actual": 99,
      "id": 21277340
    },
    "away": null
  },
  "15366480": {
    "home": null,
    "away": {
      "fractionalValue": "2/1",
      "expected": 33,
      "actual": 50,
      "id": 21276839
    }
  },
  "15519405": {
    "home": {
      "fractionalValue": "2/5",
      "expected": 71,
      "actual": 63,
      "id": 21276835
    },
    "away": null
  },
  "15603233": {
    "home": {
      "fractionalValue": "13/10",
      "expected": 43,
      "actual": 46,
      "id": 21276774
    },
    "away": {
      "fractionalValue": "7/4",
      "expected": 36,
      "actual": 53,
      "id": 21276775
    }
  },
  "15579729": {
    "home": {
      "fractionalValue": "83/100",
      "expected": 55,
      "actual": 89,
      "id": 21276766
    },
    "away": {
      "fractionalValue": "11/4",
      "expected": 27,
      "actual": 8,
      "id": 21276767
    }
  }
}